Metadata-Version: 2.1
Name: goldpirate
Version: 1.8.2
Summary: A python module to download torrents
Home-page: https://github.com/mortafix/GoldPirate
Author: Moris Doratiotto
Author-email: moris.doratiotto@gmail.com
Keywords: torrent,download
Classifier: Programming Language :: Python :: 3.8
Classifier: License :: OSI Approved :: MIT License
Classifier: Operating System :: OS Independent
Classifier: Intended Audience :: Developers
Requires-Python: >=3.8
